{
  "main": {
    "id": "02d451c9f26ae472",
    "type": "split",
    "children": [
      {
        "id": "13eda2745d0e0eb0",
        "type": "tabs",
        "children": [
          {
            "id": "66a27fba3394c885",
            "type": "leaf",
            "state": {
              "type": "markdown",
              "state": {
                "file": "daily/2025-07-06.md",
                "mode": "source",
                "source": false,
                "backlinks": true,
                "backlinkOpts": {
                  "collapseAll": false,
                  "extraContext": false,
                  "sortOrder": "alphabetical",
                  "showSearch": false,
                  "searchQuery": "",
                  "backlinkCollapsed": false,
                  "unlinkedCollapsed": true
                }
              },
              "icon": "lucide-file",
              "title": "2025-07-06"
            }
          },
          {
            "id": "c58234d76e5e78ed",
            "type": "leaf",
            "state": {
              "type": "markdown",
              "state": {
                "file": "Programming/laravel/acwa/lesson/6-validation.md",
                "mode": "preview",
                "source": false,
                "backlinks": true,
                "backlinkOpts": {
                  "collapseAll": false,
                  "extraContext": false,
                  "sortOrder": "alphabetical",
                  "showSearch": false,
                  "searchQuery": "",
                  "backlinkCollapsed": false,
                  "unlinkedCollapsed": true
                }
              },
              "icon": "lucide-file",
              "title": "6-validation"
            }
          },
          {
            "id": "4d485b3fd8539cdb",
            "type": "leaf",
            "state": {
              "type": "markdown",
              "state": {
                "file": "Economics/study/Экономическая теория/volumes/volume 31/volume 31.md",
                "mode": "source",
                "source": false,
                "backlinks": true,
                "backlinkOpts": {
                  "collapseAll": false,
                  "extraContext": false,
                  "sortOrder": "alphabetical",
                  "showSearch": false,
                  "searchQuery": "",
                  "backlinkCollapsed": false,
                  "unlinkedCollapsed": true
                }
              },
              "icon": "lucide-file",
              "title": "volume 31"
            }
          },
          {
            "id": "d28d67f5b55d82b2",
            "type": "leaf",
            "state": {
              "type": "markdown",
              "state": {
                "file": "lk.samgtu/VKR/Легенда 1.md",
                "mode": "preview",
                "source": false,
                "backlinks": true,
                "backlinkOpts": {
                  "collapseAll": false,
                  "extraContext": false,
                  "sortOrder": "alphabetical",
                  "showSearch": false,
                  "searchQuery": "",
                  "backlinkCollapsed": false,
                  "unlinkedCollapsed": true
                }
              },
              "icon": "lucide-file",
              "title": "Легенда 1"
            }
          },
          {
            "id": "ed7f362075989629",
            "type": "leaf",
            "state": {
              "type": "markdown",
              "state": {
                "file": "lk.samgtu/VKR/notes/step 2/бизнес процессы/Диаграммы.md",
                "mode": "preview",
                "source": false,
                "backlinks": true,
                "backlinkOpts": {
                  "collapseAll": false,
                  "extraContext": false,
                  "sortOrder": "alphabetical",
                  "showSearch": false,
                  "searchQuery": "",
                  "backlinkCollapsed": false,
                  "unlinkedCollapsed": true
                }
              },
              "icon": "lucide-file",
              "title": "Диаграммы"
            }
          },
          {
            "id": "8840f128d5e9420d",
            "type": "leaf",
            "state": {
              "type": "markdown",
              "state": {
                "file": "lk.samgtu/VKR/notes/step 2/2.1. Архитектура системы.md",
                "mode": "preview",
                "source": false,
                "backlinks": true,
                "backlinkOpts": {
                  "collapseAll": false,
                  "extraContext": false,
                  "sortOrder": "alphabetical",
                  "showSearch": false,
                  "searchQuery": "",
                  "backlinkCollapsed": false,
                  "unlinkedCollapsed": true
                }
              },
              "icon": "lucide-file",
              "title": "2.1. Архитектура системы"
            }
          },
          {
            "id": "2593af9b6eac0023",
            "type": "leaf",
            "state": {
              "type": "markdown",
              "state": {
                "file": "lk.samgtu/VKR/notes/step 1/2 Примерное содержание.md",
                "mode": "preview",
                "source": false,
                "backlinks": true,
                "backlinkOpts": {
                  "collapseAll": false,
                  "extraContext": false,
                  "sortOrder": "alphabetical",
                  "showSearch": false,
                  "searchQuery": "",
                  "backlinkCollapsed": false,
                  "unlinkedCollapsed": true
                }
              },
              "icon": "lucide-file",
              "title": "2 Примерное содержание"
            }
          },
          {
            "id": "64e9727d658f7dc0",
            "type": "leaf",
            "state": {
              "type": "markdown",
              "state": {
                "file": "lk.samgtu/VKR/notes/step 2/бизнес процессы/Диаграммы.md",
                "mode": "preview",
                "source": false,
                "backlinks": true,
                "backlinkOpts": {
                  "collapseAll": false,
                  "extraContext": false,
                  "sortOrder": "alphabetical",
                  "showSearch": false,
                  "searchQuery": "",
                  "backlinkCollapsed": false,
                  "unlinkedCollapsed": true
                }
              },
              "icon": "lucide-file",
              "title": "Диаграммы"
            }
          },
          {
            "id": "825e05ac3cc9e920",
            "type": "leaf",
            "state": {
              "type": "markdown",
              "state": {
                "file": "Economics/study/Экономическая теория/volumes/volume 31/volume 31.md",
                "mode": "source",
                "source": false,
                "backlinks": true,
                "backlinkOpts": {
                  "collapseAll": false,
                  "extraContext": false,
                  "sortOrder": "alphabetical",
                  "showSearch": false,
                  "searchQuery": "",
                  "backlinkCollapsed": false,
                  "unlinkedCollapsed": true
                }
              },
              "icon": "lucide-file",
              "title": "volume 31"
            }
          }
        ],
        "currentTab": 2
      }
    ],
    "direction": "vertical"
  },
  "left": {
    "id": "4a49dd92cf2aa88c",
    "type": "split",
    "children": [
      {
        "id": "688f7faeb7d3dcf9",
        "type": "tabs",
        "children": [
          {
            "id": "96dbea7db3b1f7a3",
            "type": "leaf",
            "state": {
              "type": "file-explorer",
              "state": {
                "sortOrder": "alphabetical",
                "autoReveal": false
              },
              "icon": "lucide-folder-closed",
              "title": "Files"
            }
          },
          {
            "id": "ec061cd20b1c0d6f",
            "type": "leaf",
            "state": {
              "type": "search",
              "state": {
                "query": "model_has",
                "matchingCase": false,
                "explainSearch": false,
                "collapseAll": false,
                "extraContext": false,
                "sortOrder": "alphabetical"
              },
              "icon": "lucide-search",
              "title": "Search"
            }
          },
          {
            "id": "5fb000a5b0b3e7cd",
            "type": "leaf",
            "state": {
              "type": "bookmarks",
              "state": {},
              "icon": "lucide-bookmark",
              "title": "Bookmarks"
            }
          }
        ]
      }
    ],
    "direction": "horizontal",
    "width": 254.5
  },
  "right": {
    "id": "69e258f4db20389d",
    "type": "split",
    "children": [
      {
        "id": "9db112b4f23a27ec",
        "type": "tabs",
        "children": [
          {
            "id": "0fe22d37484c9363",
            "type": "leaf",
            "state": {
              "type": "backlink",
              "state": {
                "collapseAll": false,
                "extraContext": false,
                "sortOrder": "alphabetical",
                "showSearch": false,
                "searchQuery": "",
                "backlinkCollapsed": false,
                "unlinkedCollapsed": true
              },
              "icon": "links-coming-in",
              "title": "Backlinks"
            }
          },
          {
            "id": "45bc3434bea9c1f5",
            "type": "leaf",
            "state": {
              "type": "git-view",
              "state": {},
              "icon": "git-pull-request",
              "title": "Source Control"
            }
          },
          {
            "id": "2c02c89a4a5272c0",
            "type": "leaf",
            "state": {
              "type": "outgoing-link",
              "state": {
                "file": "daily/new.md",
                "linksCollapsed": false,
                "unlinkedCollapsed": true
              },
              "icon": "lucide-file",
              "title": "Plugin no longer active"
            }
          },
          {
            "id": "82cffaa1f0c5819d",
            "type": "leaf",
            "state": {
              "type": "tag",
              "state": {
                "sortOrder": "frequency",
                "useHierarchy": true
              },
              "icon": "lucide-file",
              "title": "Plugin no longer active"
            }
          }
        ],
        "currentTab": 1
      }
    ],
    "direction": "horizontal",
    "width": 300
  },
  "left-ribbon": {
    "hiddenItems": {
      "switcher:Open quick switcher": false,
      "graph:Open graph view": false,
      "canvas:Create new canvas": false,
      "daily-notes:Open today's daily note": false,
      "command-palette:Open command palette": false,
      "obsidian-git:Open Git source control": false
    }
  },
  "active": "4d485b3fd8539cdb",
  "lastOpenFiles": [
    "6amart/Основа.md",
    "6amart/project/routes.md",
    "6amart/project/Трэк номер.md",
    "Programming/laravel/acwa/lesson/12-end.md",
    "conflict-files-obsidian-git.md",
    "Programming/laravel/acwa/lesson/11-es.md",
    "Programming/laravel/acwa/lesson/10-cqrs.md",
    "Programming/laravel/acwa/lesson/9-domain-layer.md",
    "Programming/laravel/acwa/lesson/8-unit-test.md",
    "Programming/laravel/acwa/lesson/7-events.md",
    "Programming/laravel/acwa/lesson/6-validation.md",
    "Programming/laravel/acwa/lesson/5-error-handling.md",
    "Programming/laravel/acwa/lesson/4-application-layer.md",
    "Programming/laravel/acwa/lesson/3-painless-refactoring.md",
    "Programming/laravel/acwa/lesson/2-di.md",
    "Programming/laravel/acwa/lesson/1-bad-habits.md",
    "Programming/laravel/acwa/lesson/0-intro.md",
    "Programming/laravel/acwa/Book.txt",
    "Programming/laravel/acwa/images/unit.png",
    "Programming/laravel/acwa/images/typical_product.png",
    "Programming/laravel/acwa/images/two_level_validation.png",
    "Programming/laravel/acwa/images/saga_events.png",
    "Programming/laravel/acwa/images/orchestrator.png",
    "Programming/laravel/acwa/images/oracle_cqrs.png",
    "Programming/laravel/acwa/images/master_slave_cqrs.png",
    "Programming/laravel/acwa/images/master_slave.png",
    "Programming/laravel/acwa/images/integration_testing_example.png",
    "Programming/laravel/acwa/images/hard_dependencies.png",
    "Programming/laravel/acwa/images",
    "Programming/laravel/acwa/lesson",
    "Programming/laravel/acwa",
    "Programming/laravel",
    "daily/2025-07-06.md",
    "daily/2025-07-05.md",
    "Economics/study/Экономическая теория/volumes/volume 31/Что такое модель совокупных расходов.md",
    "Economics/study/Экономическая теория/volumes/volume 31/questions/8.md",
    "Economics/study/Экономическая теория/volumes/volume 31/questions/7.md",
    "Economics/study/Экономическая теория/volumes/volume 31/questions/6.md",
    "lk.samgtu/VKR/Текст выступления.md",
    "Programming/Отчет.md",
    "Programming/Как изучать ASP.NET в информационной системах.md",
    "Programming/История ОС UNIX/IMG/Без названия.jfif",
    "Programming/История ОС UNIX/IMG",
    "Programming/История ОС UNIX/archlinux_setting",
    "Programming/История ОС UNIX",
    "Programming/patterns/async_programming/list",
    "Untitled 3.canvas",
    "Untitled 2.canvas",
    "Untitled.canvas",
    "Untitled 1.canvas"
  ]
}