{
  "main": {
    "id": "02d451c9f26ae472",
    "type": "split",
    "children": [
      {
        "id": "30c5b326b6cb8ec7",
        "type": "tabs",
        "children": [
          {
            "id": "e5102369350b88d5",
            "type": "leaf",
            "state": {
              "type": "markdown",
              "state": {
                "file": "daily/2025-02-02.md",
                "mode": "source",
                "backlinks": true,
                "source": false
              },
              "icon": "lucide-file",
              "title": "2025-02-02"
            }
          },
          {
            "id": "4886c63cef28c3a3",
            "type": "leaf",
            "state": {
              "type": "markdown",
              "state": {
                "file": "Economics/volumes/volume 12/(7) Регулируемая монополия.md",
                "mode": "preview",
                "source": false,
                "backlinks": true,
                "backlinkOpts": {
                  "collapseAll": false,
                  "extraContext": false,
                  "sortOrder": "alphabetical",
                  "showSearch": false,
                  "searchQuery": "",
                  "backlinkCollapsed": false,
                  "unlinkedCollapsed": true
                }
              },
              "icon": "lucide-file",
              "title": "(7) Регулируемая монополия"
            }
          },
          {
            "id": "d5bcc862efeb9a12",
            "type": "leaf",
            "state": {
              "type": "markdown",
              "state": {
                "file": "daily/2025-02-15.md",
                "mode": "source",
                "source": false,
                "backlinks": true,
                "backlinkOpts": {
                  "collapseAll": false,
                  "extraContext": false,
                  "sortOrder": "alphabetical",
                  "showSearch": false,
                  "searchQuery": "",
                  "backlinkCollapsed": false,
                  "unlinkedCollapsed": true
                }
              },
              "icon": "lucide-file",
              "title": "2025-02-15"
            }
          },
          {
            "id": "74ff1c191be57f7a",
            "type": "leaf",
            "state": {
              "type": "markdown",
              "state": {
                "file": "conflict-files-obsidian-git.md",
                "mode": "preview",
                "source": false,
                "backlinks": true,
                "backlinkOpts": {
                  "collapseAll": false,
                  "extraContext": false,
                  "sortOrder": "alphabetical",
                  "showSearch": false,
                  "searchQuery": "",
                  "backlinkCollapsed": false,
                  "unlinkedCollapsed": true
                }
              },
              "icon": "lucide-file",
              "title": "conflict-files-obsidian-git"
            }
          },
          {
            "id": "1062c9aef33ab452",
            "type": "leaf",
            "state": {
              "type": "markdown",
              "state": {
                "file": "Economics/volume 3.md",
                "mode": "preview",
                "backlinks": true,
                "source": false
              },
              "icon": "lucide-file",
              "title": "volume 3"
            }
          },
          {
            "id": "96ca7029b8720bf6",
            "type": "leaf",
            "state": {
              "type": "markdown",
              "state": {
                "file": "Economics/volume 3.md",
                "mode": "preview",
                "backlinks": true,
                "source": false
              },
              "icon": "lucide-file",
              "title": "volume 3"
            }
          },
          {
            "id": "b1d269a522b666e3",
            "type": "leaf",
            "state": {
              "type": "markdown",
              "state": {
                "file": "Economics/volume 3.md",
                "mode": "preview",
                "backlinks": true,
                "source": false
              },
              "icon": "lucide-file",
              "title": "volume 3"
            }
          },
          {
            "id": "3e74a1883f3ab261",
            "type": "leaf",
            "state": {
              "type": "markdown",
              "state": {
                "file": "Economics/volume 6/Эластичность.md",
                "mode": "source",
                "backlinks": true,
                "source": false
              },
              "icon": "lucide-file",
              "title": "Эластичность"
            }
          },
          {
            "id": "8cf27799ab1011de",
            "type": "leaf",
            "state": {
              "type": "markdown",
              "state": {
                "file": "Economics/volume 6/Эластичность.md",
                "mode": "preview",
                "backlinks": true,
                "source": false
              },
              "icon": "lucide-file",
              "title": "Эластичность"
            }
          },
          {
            "id": "3aa5e64491fbf76e",
            "type": "leaf",
            "state": {
              "type": "markdown",
              "state": {
                "file": "Economics/theme/material/Рынки в экономике.md",
                "mode": "source",
                "backlinks": true,
                "source": false
              },
              "icon": "lucide-file",
              "title": "Рынки в экономике"
            }
          }
        ],
        "currentTab": 3
      }
    ],
    "direction": "vertical"
  },
  "left": {
    "id": "4a49dd92cf2aa88c",
    "type": "split",
    "children": [
      {
        "id": "688f7faeb7d3dcf9",
        "type": "tabs",
        "children": [
          {
            "id": "96dbea7db3b1f7a3",
            "type": "leaf",
            "state": {
              "type": "file-explorer",
              "state": {
                "sortOrder": "alphabetical",
                "autoReveal": false
              },
              "icon": "lucide-folder-closed",
              "title": "Files"
            }
          },
          {
            "id": "ec061cd20b1c0d6f",
            "type": "leaf",
            "state": {
              "type": "search",
              "state": {
                "query": "Список ключевых графиков",
                "matchingCase": false,
                "explainSearch": false,
                "collapseAll": false,
                "extraContext": false,
                "sortOrder": "alphabetical"
              },
              "icon": "lucide-search",
              "title": "Search"
            }
          },
          {
            "id": "5fb000a5b0b3e7cd",
            "type": "leaf",
            "state": {
              "type": "bookmarks",
              "state": {},
              "icon": "lucide-bookmark",
              "title": "Bookmarks"
            }
          }
        ]
      }
    ],
    "direction": "horizontal",
    "width": 351.5
  },
  "right": {
    "id": "69e258f4db20389d",
    "type": "split",
    "children": [
      {
        "id": "9db112b4f23a27ec",
        "type": "tabs",
        "children": [
          {
            "id": "0fe22d37484c9363",
            "type": "leaf",
            "state": {
              "type": "backlink",
              "state": {
                "file": "Economics/elastic.md",
                "collapseAll": false,
                "extraContext": false,
                "sortOrder": "alphabetical",
                "showSearch": false,
                "searchQuery": "",
                "backlinkCollapsed": false,
                "unlinkedCollapsed": true
              },
              "icon": "links-coming-in",
              "title": "Backlinks for elastic"
            }
          },
          {
            "id": "45bc3434bea9c1f5",
            "type": "leaf",
            "state": {
              "type": "git-view",
              "state": {},
              "icon": "git-pull-request",
              "title": "Source Control"
            }
          }
        ],
        "currentTab": 1
      }
    ],
    "direction": "horizontal",
    "width": 333.5
  },
  "left-ribbon": {
    "hiddenItems": {
      "switcher:Open quick switcher": false,
      "graph:Open graph view": false,
      "canvas:Create new canvas": false,
      "daily-notes:Open today's daily note": false,
      "command-palette:Open command palette": false,
      "obsidian-git:Open Git source control": false
    }
  },
  "active": "74ff1c191be57f7a",
  "lastOpenFiles": [
    "daily/2025-02-15.md",
    "conflict-files-obsidian-git.md",
    "delay/Pasted image 20250206124311.png",
    "delay",
    "daily/2025-02-04.md",
    "Untitled.md",
    "Economics/volumes/volume 12/(1) Характеристики монополии.md",
    "Economics/volumes/volume 13/(1) Монополистическая конкуренция.md",
    "Economics/volumes/volume 13/(4) Разнообразие продукции.md",
    "Economics/volumes/volume 13/volume 13.md",
    "Economics/volumes/volume 13/(3) Монополистическая конкуренция и эффективность.md",
    "Economics/volumes/volume 9/Экономические издержки.md",
    "Economics/volumes/volume 9/Производственные зависимости краткосрочного периода.md",
    "Economics/volumes/volume 9/Предельные издержки.md",
    "Economics/volumes/volume 9/Краткосрочный период и их издержки.md",
    "Economics/volumes/volume 10/мысль.md",
    "Economics/volumes/volume 10/Максиммизация прибыли в краткосрочной перспективе на основе сравнения совокупного дохода и общих издержек.md",
    "Economics/volumes/volume 10/Конкуренция рынка.md",
    "Economics/volumes/volume 11.md",
    "Economics/volumes/volume 10/volume 10.md",
    "Economics/volumes/volume 13/(2) Цена и объем продукции при монополистической конкуренции.md",
    "Economics/volumes/volume 12/ценовую и неценовую конкуренцию.md",
    "Economics/volumes/volume 12/(7) Регулируемая монополия.md",
    "Economics/volumes/volume 12/(5) Экономических эффекты монополии.md",
    "Economics/volumes/volume 12/(4) Определение обьем производства и цены.md",
    "Economics/volumes/volume 12/(3) Монопольный спрос.md",
    "Economics/volumes/volume 6/elastic.md",
    "Economics/volumes/volume 6/Эластичность.md",
    "Projects/Mincraft Server",
    "Projects/Courses/CRUD",
    "Economics/volumes/volume 14",
    "Economics/volumes/volume 13",
    "Economics/volumes/volume 12",
    "Economics/theme/material/Econimica sovershi",
    "lk.samgtu",
    "Projects/Courses/info",
    "Projects/Plan",
    "Untitled 1.canvas",
    "Untitled.canvas",
    "Programming/История ОС UNIX/IMG/Nokia_Bell_Labs_Murray_Hill,_NJ.jpg",
    "Programming/История ОС UNIX/IMG/Bell_Labs_HQ.png",
    "Programming/История ОС UNIX/IMG/930ba80dfbd79c7ac1956897576cf166.jpg",
    "Programming/old/data_structure/Pasted image 20220215221220.png",
    "Programming/old/data_structure/Pasted image 20220215221026.png",
    "Programming/Computer_Science/Lecture_1/Pasted image 20220124023700.png",
    "Programming/Pasted image 20230907194244.png",
    "Programming/Pasted image 20230907192719.png",
    "Programming/Pasted image 20230907113832.png"
  ]
}